PARIKernel/io.cpython-314-darwin.so
PARIKernel/__init__.py
PARIKernel/io.pyx
PARIKernel/io.pxd
PARIKernel/paridecl.pxd
PARIKernel/kernel.cpython-314-darwin.so
PARIKernel/kernel.pyx
PARIKernel/svg.cpython-314-darwin.so
PARIKernel/svg.pyx
PARIKernel/__main__.py
passagemath_pari/__init__.py
passagemath_pari/.dylibs/libgmpxx.4.dylib
passagemath_pari/.dylibs/libreadline.8.2.dylib
passagemath_pari/.dylibs/libntl.45.dylib
passagemath_pari/.dylibs/libgsl.28.dylib
passagemath_pari/.dylibs/libxeus-zmq.6.0.1.dylib
passagemath_pari/.dylibs/libgf2x.3.dylib
passagemath_pari/.dylibs/libgivaro.9.dylib
passagemath_pari/.dylibs/libcrypto.3.dylib
passagemath_pari/.dylibs/libflint.22.0.dylib
passagemath_pari/.dylibs/libopenblasp-r0.3.29.dylib
passagemath_pari/.dylibs/libgfortran.5.dylib
passagemath_pari/.dylibs/libpari-gmp-tls.dylib
passagemath_pari/.dylibs/libzmq.5.dylib
passagemath_pari/.dylibs/libquadmath.0.dylib
passagemath_pari/.dylibs/libxeus.13.1.0.dylib
passagemath_pari/.dylibs/libgmp.10.dylib
passagemath_pari/.dylibs/libmpfr.6.dylib
passagemath_pari-10.6.43.dist-info/RECORD
passagemath_pari-10.6.43.dist-info/WHEEL
passagemath_pari-10.6.43.dist-info/top_level.txt
passagemath_pari-10.6.43.dist-info/METADATA
passagemath_pari-10.6.43.data/data/etc/jupyter/nbconfig/notebook.d/gp-mode.json
passagemath_pari-10.6.43.data/data/share/jupyter/kernels/xeus-gp/kernel.json
passagemath_pari-10.6.43.data/data/share/jupyter/kernels/xeus-gp/logo-64x64.png
passagemath_pari-10.6.43.data/data/share/jupyter/kernels/xeus-gp/logo-32x32.png
passagemath_pari-10.6.43.data/data/share/jupyter/kernels/xeus-gp/logo-svg.svg
passagemath_pari-10.6.43.data/data/share/jupyter/kernels/pari_jupyter/kernel.json
passagemath_pari-10.6.43.data/data/share/jupyter/kernels/pari_jupyter/kernel.js
passagemath_pari-10.6.43.data/data/share/jupyter/kernels/pari_jupyter/logo-64x64.png
passagemath_pari-10.6.43.data/data/share/jupyter/nbextensions/gp-mode/gp.js
passagemath_pari-10.6.43.data/data/share/jupyter/nbextensions/gp-mode/main.js
sage_wheels/bin/gp2c-run
sage_wheels/bin/gp2c
sage_wheels/bin/gp
sage_wheels/bin/xeus-gp
sage_wheels/share/gp2c/func.dsc
