Metadata-Version: 2.4
Name: passagemath-pari
Version: 10.6.43
Summary: passagemath: Computational Number Theory with PARI/GP
Author-email: The Sage Developers <sage-support@googlegroups.com>
Maintainer: Matthias Köppe, passagemath contributors
License-Expression: GPL-2.0-or-later
Project-URL: release notes, https://github.com/passagemath/passagemath/releases
Project-URL: repo (upstream), https://github.com/sagemath/sage
Project-URL: repo, https://github.com/passagemath/passagemath
Project-URL: documentation, https://passagemath.org/docs/latest
Project-URL: homepage (upstream), https://www.sagemath.org
Project-URL: discourse, https://passagemath.discourse.group
Project-URL: tracker (upstream), https://github.com/sagemath/sage/issues
Project-URL: tracker, https://github.com/passagemath/passagemath/issues
Classifier: Development Status :: 6 - Mature
Classifier: Intended Audience :: Education
Classifier: Intended Audience :: Science/Research
Classifier: Operating System :: POSIX
Classifier: Operating System :: POSIX :: Linux
Classifier: Operating System :: MacOS :: MacOS X
Classifier: Programming Language :: Python :: 3 :: Only
Classifier: Programming Language :: Python :: 3.10
Classifier: Programming Language :: Python :: 3.11
Classifier: Programming Language :: Python :: 3.12
Classifier: Programming Language :: Python :: 3.13
Classifier: Programming Language :: Python :: 3.14
Classifier: Programming Language :: Python :: Implementation :: CPython
Classifier: Topic :: Scientific/Engineering :: Mathematics
Requires-Python: <3.15,>=3.10
Requires-Dist: cysignals!=1.12.4; sys_platform == "win32"
Requires-Dist: cysignals!=1.12.0,>=1.11.2
Requires-Dist: memory_allocator
Requires-Dist: passagemath-environment~=10.6.43.0
Requires-Dist: passagemath-categories~=10.6.43.0
Requires-Dist: conway-polynomials>=0.8
Provides-Extra: test
Requires-Dist: passagemath-repl; extra == "test"
Provides-Extra: elldata
Requires-Dist: passagemath-pari-elldata; extra == "elldata"
Provides-Extra: galdata
Requires-Dist: passagemath-pari-galdata; extra == "galdata"
Provides-Extra: galpol
Requires-Dist: passagemath-pari-galpol; extra == "galpol"
Provides-Extra: nflistdata
Requires-Dist: passagemath-pari-nflistdata; extra == "nflistdata"
Provides-Extra: nftables
Requires-Dist: passagemath-pari-nftables; extra == "nftables"
Provides-Extra: seadata
Requires-Dist: passagemath-pari-seadata; extra == "seadata"
Provides-Extra: seadata-big
Requires-Dist: passagemath-pari-seadata-big; extra == "seadata-big"
Provides-Extra: seadata-small
Requires-Dist: passagemath-pari-seadata-small; extra == "seadata-small"
Provides-Extra: jupyterkernel
Requires-Dist: ipykernel>=5.2.1; extra == "jupyterkernel"
Provides-Extra: jupyterlab
Requires-Dist: passagemath-pari[jupyterkernel]; extra == "jupyterlab"
Requires-Dist: jupyterlab; extra == "jupyterlab"
Provides-Extra: notebook
Requires-Dist: passagemath-pari[jupyterkernel]; extra == "notebook"
Requires-Dist: notebook>=6.1.1; extra == "notebook"
Provides-Extra: standard
Requires-Dist: passagemath-pari[galdata,seadata-small]; extra == "standard"
